MANIFEST.in
README.md
airflow.txt
dev.txt
setup.py
treasury/__init__.py
treasury/api.py
treasury/version.txt
treasury.egg-info/PKG-INFO
treasury.egg-info/SOURCES.txt
treasury.egg-info/dependency_links.txt
treasury.egg-info/entry_points.txt
treasury.egg-info/requires.txt
treasury.egg-info/top_level.txt
treasury/airflow/__init__.py
treasury/airflow/hooks.py
treasury/airflow/operators.py